nparray2pil
