Metadata-Version: 2.1
Name: nparray2pil
Version: 0.0.3
Summary: Converts numpy arrays into images.
Home-page: https://github.com/abhinav-gg/nparray2pil/
Author: Abhinav G, Oliver Gibson
Author-email: agupta.cam7@gmail.com
License: MIT
Keywords: np,array,pil,convertion,convert,opencv,array to pil
Platform: UNKNOWN
Classifier: Programming Language :: Python :: 3
Classifier: License :: OSI Approved :: MIT License
Classifier: Operating System :: OS Independent
